[
  {
    "_id": "5645fd5662047212024e51c7",
    "user": {
      "_id": "5645fc71890ca80f02ae4dd7",
      "name": "Brian"
    },
    "category": {
      "_id": "5645fcd1a01ca905ef611b5c",
      "name": "Push Ups",
      "description": "Push ups in 2 minutes",
      "dataType": "number",
      "goalType": "most"
    },
    "itemValue": "20",
    "notes": "First day at ST",
    "__v": 0,
    "itemDateTime": "2012-08-01T18:11:57.000Z"
  },
  {
    "_id": "5645fd3b62047212024e51c6",
    "user": {
      "_id": "5645fc71890ca80f02ae4dd7",
      "name": "Brian"
    },
    "category": {
      "_id": "5645fcd1a01ca905ef611b5b",
      "name": "Sit Ups",
      "description": "Sit ups in 2 minutes",
      "dataType": "number",
      "goalType": "most"
    },
    "itemValue": "4",
    "notes": "First day at ST",
    "__v": 0,
    "itemDateTime": "2012-08-01T18:11:57.000Z"
  },
  {
    "_id": "5645fd6962047212024e51c8",
    "user": {
      "_id": "5645fc71890ca80f02ae4dd7",
      "name": "Brian"
    },
    "category": {
      "_id": "5645fcd1a01ca905ef611b5d",
      "name": "Pull Ups",
      "description": "Maximum number of pull ups",
      "dataType": "number",
      "goalType": "most"
    },
    "itemValue": "0",
    "notes": "First day at ST",
    "__v": 0,
    "itemDateTime": "2012-08-01T18:11:57.000Z"
  },
  {
    "_id": "5645fd7a62047212024e51c9",
    "user": {
      "_id": "5645fc71890ca80f02ae4dd7",
      "name": "Brian"
    },
    "category": {
      "_id": "5645fcd1a01ca905ef611b5e",
      "name": "1.5 Mile Run",
      "description": "Time in minutes and seconds to run 1.5 miles",
      "dataType": "time",
      "goalType": "least"
    },
    "itemValue": "17:22",
    "notes": "First day at ST",
    "__v": 0,
    "itemDateTime": "2012-08-01T18:11:57.000Z"
  },
  {
    "_id": "564d3b881810e78d0ce61850",
    "user": {
      "_id": "5645fc71890ca80f02ae4dd7",
      "name": "Brian"
    },
    "category": {
      "_id": "5645fcd1a01ca905ef611b5e",
      "name": "1.5 Mile Run",
      "description": "Time in minutes and seconds to run 1.5 miles",
      "dataType": "time",
      "goalType": "least"
    },
    "itemValue": "15:11",
    "notes": "",
    "__v": 0,
    "itemDateTime": "2012-08-11T18:11:57.000Z"
  },
  {
    "_id": "564d3b971810e78d0ce61851",
    "user": {
      "_id": "5645fc71890ca80f02ae4dd7",
      "name": "Brian"
    },
    "category": {
      "_id": "5645fcd1a01ca905ef611b5d",
      "name": "Pull Ups",
      "description": "Maximum number of pull ups",
      "dataType": "number",
      "goalType": "most"
    },
    "itemValue": "1",
    "notes": "",
    "__v": 0,
    "itemDateTime": "2012-08-11T18:11:57.000Z"
  },
  {
    "_id": "564d3ba41810e78d0ce61852",
    "user": {
      "_id": "5645fc71890ca80f02ae4dd7",
      "name": "Brian"
    },
    "category": {
      "_id": "5645fcd1a01ca905ef611b5c",
      "name": "Push Ups",
      "description": "Push ups in 2 minutes",
      "dataType": "number",
      "goalType": "most"
    },
    "itemValue": "33",
    "notes": "First day at ST",
    "__v": 0,
    "itemDateTime": "2012-08-12T18:11:57.000Z"
  },
  {
    "_id": "564d3bbd1810e78d0ce61853",
    "user": {
      "_id": "5645fc71890ca80f02ae4dd7",
      "name": "Brian"
    },
    "category": {
      "_id": "5645fcd1a01ca905ef611b5b",
      "name": "Sit Ups",
      "description": "Sit ups in 2 minutes",
      "dataType": "number",
      "goalType": "most"
    },
    "itemValue": "9",
    "notes": "",
    "__v": 0,
    "itemDateTime": "2012-08-13T18:11:57.000Z"
  }
]
